vagueify/__init__.py
vagueify/vagueify.py
vagueify-0.0.1.data/scripts/vague_all.sh
vagueify-0.0.1.dist-info/LICENSE
vagueify-0.0.1.dist-info/METADATA
vagueify-0.0.1.dist-info/WHEEL
vagueify-0.0.1.dist-info/top_level.txt
vagueify-0.0.1.dist-info/zip-safe
vagueify-0.0.1.dist-info/RECORD
